MANIFEST.in
Makefile
requirements.readthedocs.txt
requirements.txt
setup.py
doc/Makefile
doc/conf.py
dockerfiles/base/Dockerfile
dockerfiles/base/rabbitmq.sh
dockerfiles/drone/Dockerfile
dockerfiles/drone/drone.patch
dockerfiles/drone/drone_notes.txt
mltsp/__init__.py
mltsp/build_model.py
mltsp/celery_task_tools.py
mltsp/celery_tasks.py
mltsp/cfg.py
mltsp/custom_exceptions.py
mltsp/custom_feature_tools.py
mltsp/featurize.py
mltsp/generate_ipynb.py
mltsp/log.py
mltsp/mltsp.yaml.example
mltsp/obs_feature_tools.py
mltsp/predict_class.py
mltsp/science_feature_tools.py
mltsp/setup.py
mltsp/util.py
mltsp/version.py
mltsp.egg-info/PKG-INFO
mltsp.egg-info/SOURCES.txt
mltsp.egg-info/dependency_links.txt
mltsp.egg-info/entry_points.txt
mltsp.egg-info/not-zip-safe
mltsp.egg-info/requires.txt
mltsp.egg-info/top_level.txt
mltsp/Flask/__init__.py
mltsp/Flask/flask_app.py
mltsp/Flask/static/jquery-ui-1.10.4/AUTHORS.txt
mltsp/Flask/static/jquery-ui-1.10.4/MIT-LICENSE.txt
mltsp/Flask/static/jquery-ui-1.10.4/tests/unit/autocomplete/remote_object_array_labels.txt
mltsp/Flask/static/jquery-ui-1.10.4/tests/unit/autocomplete/remote_object_array_values.txt
mltsp/Flask/static/jquery-ui-1.10.4/tests/unit/autocomplete/remote_string_array.txt
mltsp/Flask/static/jquery-ui/development-bundle/AUTHORS.txt
mltsp/Flask/static/jquery-ui/development-bundle/GPL-LICENSE.txt
mltsp/Flask/static/jquery-ui/development-bundle/MIT-LICENSE.txt
mltsp/Flask/static/js/flot/API.txt
mltsp/Flask/static/js/flot/FAQ.txt
mltsp/Flask/static/js/flot/LICENSE.txt
mltsp/Flask/static/js/flot/NEWS.txt
mltsp/Flask/static/js/flot/PLUGINS.txt
mltsp/Flask/static/js/flot/README.txt
mltsp/custom_feature_scripts/__init__.py
mltsp/data/sample_data/215153_215176_218272_218934.tar.gz
mltsp/data/sample_data/215153_215176_218272_218934_metadata.dat
mltsp/data/sample_data/215153_metadata.dat
mltsp/data/sample_data/asas_training_set.tar.gz
mltsp/data/sample_data/asas_training_set_classes.dat
mltsp/data/sample_data/asas_training_set_classes_with_metadata.dat
mltsp/data/sample_data/asas_training_subset.tar.gz
mltsp/data/sample_data/asas_training_subset_classes.dat
mltsp/data/sample_data/asas_training_subset_classes_with_metadata.dat
