Metadata-Version: 1.1
Name: mltsp
Version: 0.3.3
Summary: Machine Learning Time-Series Platform
Home-page: http://mltsp.io
Author: MLTSP Team
Author-email: stefanv@berkeley.edu
License: Modified BSD
Download-URL: https://github.com/mltsp/mltsp
Platform: UNKNOWN
Classifier: Development Status :: 4 - Beta
Classifier: Environment :: Console
Classifier: Intended Audience :: Developers
Classifier: Intended Audience :: Science/Research
Classifier: License :: OSI Approved :: BSD License
Classifier: Programming Language :: C
Classifier: Programming Language :: Python :: 2
Classifier: Topic :: Scientific/Engineering
Classifier: Operating System :: Microsoft :: Windows
Classifier: Operating System :: POSIX
Classifier: Operating System :: Unix
Classifier: Operating System :: MacOS
Requires: beautifulsoup4
Requires: flask
Requires: Flask_Stormpath
Requires: docker_py
Requires: numpy (>= 1.8)
Requires: scipy (>= 0.13)
Requires: scikit_learn (== 0.16.1)
Requires: pandas (>= 0.13)
Requires: parse
Requires: psutil (>= 2.2.1)
Requires: rethinkdb
Requires: requests
Requires: simplejson
Requires: colorlog
Requires: matplotlib (>= 1.1)
Requires: nose
Requires: nose_exclude
Requires: pyyaml
Requires: waitress
Requires: celery
Requires: toolz
Requires: dask
